secret_key/__init__.py
secret_key/secret_key.py
DjangoSecretKey-0.1.0.dist-info/LICENSE
DjangoSecretKey-0.1.0.dist-info/METADATA
DjangoSecretKey-0.1.0.dist-info/WHEEL
DjangoSecretKey-0.1.0.dist-info/top_level.txt
DjangoSecretKey-0.1.0.dist-info/RECORD
