Metadata-Version: 2.1
Name: DjangoSecretKey
Version: 0.1.0
Summary: Django SECRET_KEY management
Home-page: https://github.com/blinglnav/djangosecretkey
Author: Min Choro
Author-email: blinglnav@gmail.com
License: MIT
Keywords: django,secret_key,secret
Platform: UNKNOWN
Classifier: Programming Language :: Python :: 3
Classifier: Programming Language :: Python :: 3.6
Requires-Python: >=3.6
Requires-Dist: pytest
